{
   "PointExSku" : 0,
   "browse" : "WeiXin",
   "discount" : "0.00",
   "env" : 1,
   "errMsg" : "",
   "hasMemPoint" : 1,
   "hasPin" : 0,
   "iRet" : 0,
   "lmVender" : 0,
   "login" : 0,
   "logoUrl" : "//img30.360buyimg.com/popshop/jfs/t1/149793/34/5979/16019/5f3e3d14E9af91329/73fe192c3292facf.jpg",
   "memLeveRuleListJson" : [],
   "member" : 0,
   "memberLevel" : 0,
   "memberPoints" : 0,
   "memberTradeCount" : 0,
   "merberTradeAmount" : "0.00",
   "openVip" : 1,
   "pointExCoupon" : 0,
   "shopId" : 118350,
   "shopLatestSignUrl" : "//img12.360buyimg.com/cms/jfs/t1/132044/8/7628/5569/5f3f905cEd1c15f35/d40f88c6edbcd120.jpg",
   "shopName" : "鹿人袜业官方旗舰店",
   "time" : 1613563912,
   "totalScore" : "",
   "venderId" : 121355
}
