{
   "PointExSku" : 0,
   "browse" : "WeiXin",
   "discount" : "0.00",
   "env" : 1,
   "errMsg" : "",
   "hasMemPoint" : 1,
   "hasPin" : 0,
   "iRet" : 0,
   "lmVender" : 0,
   "login" : 0,
   "logoUrl" : "//img30.360buyimg.com/popshop/jfs/t1/119040/26/5388/4147/5eb3a869E99480d25/6de4e8409eaf3365.jpg",
   "memLeveRuleListJson" : [],
   "member" : 0,
   "memberLevel" : 0,
   "memberPoints" : 0,
   "memberTradeCount" : 0,
   "merberTradeAmount" : "0.00",
   "openVip" : 1,
   "pointExCoupon" : 0,
   "shopId" : 10208684,
   "shopLatestSignUrl" : "//img10.360buyimg.com/cms/jfs/t1/119120/39/7516/1394/5ec37c80E7162799c/f463a32d320881ad.png",
   "shopName" : "ZGO京东自营旗舰店",
   "time" : 1613563305,
   "totalScore" : "",
   "venderId" : 10343545
}
