{
   "PointExSku" : 0,
   "browse" : "WeiXin",
   "discount" : "0.00",
   "env" : 1,
   "errMsg" : "",
   "hasMemPoint" : 1,
   "hasPin" : 0,
   "iRet" : 0,
   "lmVender" : 0,
   "login" : 0,
   "logoUrl" : "//img14.360buyimg.com/cms/jfs/t24943/81/551640361/8070/7393081a/5b73d143N1300fd75.jpg",
   "memLeveRuleListJson" : [],
   "member" : 0,
   "memberLevel" : 0,
   "memberPoints" : 0,
   "memberTradeCount" : 0,
   "merberTradeAmount" : "0.00",
   "openVip" : 1,
   "pointExCoupon" : 0,
   "shopId" : 1000110961,
   "shopLatestSignUrl" : "//img12.360buyimg.com/cms/jfs/t23620/299/2056454757/231649/b443d27/5b73d697N2e568cab.jpg",
   "shopName" : "亚之杰玩具（YA ZHI JIE WAN JU）京东自营旗舰店",
   "time" : 1613562199,
   "totalScore" : "",
   "venderId" : 1000110961
}
