{
   "PointExSku" : 0,
   "browse" : "WeiXin",
   "discount" : "0.00",
   "env" : 1,
   "errMsg" : "",
   "hasMemPoint" : 1,
   "hasPin" : 0,
   "iRet" : 0,
   "lmVender" : 0,
   "login" : 0,
   "logoUrl" : "//img12.360buyimg.com/cms/jfs/t1/26836/35/2741/3497/5c2043adE1eecbb6b/f2b19b59341a4f0c.png",
   "memLeveRuleListJson" : [],
   "member" : 0,
   "memberLevel" : 0,
   "memberPoints" : 0,
   "memberTradeCount" : 0,
   "merberTradeAmount" : "0.00",
   "openVip" : 1,
   "pointExCoupon" : 0,
   "shopId" : 1000134282,
   "shopLatestSignUrl" : "//img30.360buyimg.com/cms/jfs/t16936/264/1681570577/52086/e47956d7/5ad3fff1Ncf4ec060.png",
   "shopName" : "纽曼（Newsmy）应急电源京东自营旗舰店",
   "time" : 1613557442,
   "totalScore" : "",
   "venderId" : 1000134282
}
