{
   "PointExSku" : 0,
   "browse" : "WeiXin",
   "discount" : "0.00",
   "env" : 1,
   "errMsg" : "",
   "hasMemPoint" : 0,
   "hasPin" : 0,
   "iRet" : 0,
   "lmVender" : 0,
   "login" : 0,
   "logoUrl" : "//img10.360buyimg.com/zx/jfs/t17989/285/594149328/14581/2adf18e1/5a98a35eN7019e4a6.png",
   "memLeveRuleListJson" : [],
   "member" : 0,
   "memberLevel" : 0,
   "memberPoints" : 0,
   "memberTradeCount" : 0,
   "merberTradeAmount" : "0.00",
   "openVip" : 1,
   "pointExCoupon" : 0,
   "shopId" : 37004,
   "shopLatestSignUrl" : "//img12.360buyimg.com/jshopm/jfs/t973/354/1302370272/108567/215ac4e6/55911418N3ba6b85b.jpg",
   "shopName" : "帝洛驰饰履专卖店",
   "time" : 1613564269,
   "totalScore" : "",
   "venderId" : 39089
}
