{"code":200,"data":{"userActivityStatus":1,"continuePrizeRuleList":[{"level":7,"prizeList":[{"batchKey":"vender_BA#dc85df52b3c846acaa0f2425399f431a","prizeStartTime":1614096000000,"expireType":1,"bindType":1,"discount":16.00,"type":1,"number":10000,"budgetNum":10000,"userPirzeStatus":1,"quota":79.00,"prizeEndTime":1616601599000,"validateDay":10,"class":"com.jd.interact.center.client.api.user.domain.InteractUserPrize","status":2}],"signType":1,"days":7,"class":"com.jd.interact.center.client.api.color.domain.sign.ShopSignInteractUserPrizeRule"}],"activityName":"签到有礼","venderId":635033,"activityStatus":2,"startTime":1614096000000,"endTime":1616601599000,"id":10251558,"class":"com.jd.interact.center.client.api.color.domain.sign.ShopSignActivity","prizeRuleList":[]},"class":"com.jd.interact.center.client.api.common.param.Results","success":true}