{
   "PointExSku" : 0,
   "browse" : "WeiXin",
   "discount" : "0.00",
   "env" : 1,
   "errMsg" : "",
   "hasMemPoint" : 0,
   "hasPin" : 0,
   "iRet" : 0,
   "lmVender" : 0,
   "login" : 0,
   "logoUrl" : "//img14.360buyimg.com/cms/jfs/t1/32613/26/3249/18466/5c738b0bEa6441633/545163b25462d4ef.jpg",
   "memLeveRuleListJson" : [],
   "member" : 0,
   "memberLevel" : 0,
   "memberPoints" : 0,
   "memberTradeCount" : 0,
   "merberTradeAmount" : "0.00",
   "openVip" : 0,
   "pointExCoupon" : 0,
   "shopId" : 946744,
   "shopLatestSignUrl" : "//img11.360buyimg.com/cms/jfs/t1/8611/4/15528/37645/5c73913aE2e16f5d3/9d90583ad11a3d4c.jpg",
   "shopName" : "麦子（衡阳）运动户外专营店",
   "time" : 1613554783,
   "totalScore" : "",
   "venderId" : 10102392
}
