{
   "PointExSku" : 0,
   "browse" : "WeiXin",
   "discount" : "0.00",
   "env" : 1,
   "errMsg" : "",
   "hasMemPoint" : 0,
   "hasPin" : 0,
   "iRet" : 0,
   "lmVender" : 0,
   "login" : 0,
   "logoUrl" : "//img30.360buyimg.com/popshop/jfs/t29305/229/1420601623/8794/20debfe4/5cde54cfN7638f58f.jpg",
   "memLeveRuleListJson" : [],
   "member" : 0,
   "memberLevel" : 0,
   "memberPoints" : 0,
   "memberTradeCount" : 0,
   "merberTradeAmount" : "0.00",
   "openVip" : 0,
   "pointExCoupon" : 0,
   "shopId" : 1000161581,
   "shopLatestSignUrl" : "//img13.360buyimg.com/cms/jfs/t1/119915/14/14843/366808/5f87e146Efe6818be/d65e780ca8ccefa7.jpg",
   "shopName" : "AUTOBACS京东海外自营旗舰店",
   "time" : 1613557484,
   "totalScore" : "",
   "venderId" : 1000161581
}
