{"code":200,"data":{"userActivityStatus":1,"continuePrizeRuleList":[{"level":3,"prizeList":[{"batchKey":"vender_BA#75642620819e468287f6424b07739dda","prizeStartTime":1610812800000,"expireType":1,"bindType":1,"discount":5.00,"type":1,"number":1000,"budgetNum":1000,"userPirzeStatus":1,"quota":100.00,"prizeEndTime":1613404799000,"validateDay":7,"class":"com.jd.interact.center.client.api.user.domain.InteractUserPrize","status":2}],"signType":1,"days":3,"class":"com.jd.interact.center.client.api.color.domain.sign.ShopSignInteractUserPrizeRule"}],"activityName":"签到","venderId":217610,"activityStatus":2,"startTime":1610812800000,"endTime":1613404799000,"id":10249838,"class":"com.jd.interact.center.client.api.color.domain.sign.ShopSignActivity","prizeRuleList":[{"level":0,"prizeList":[{"discount":1.00,"type":4,"number":10000,"budgetNum":10000,"userPirzeStatus":1,"class":"com.jd.interact.center.client.api.user.domain.InteractUserPrize","status":2}],"class":"com.jd.interact.center.client.api.color.domain.sign.ShopSignInteractUserPrizeRule"}]},"class":"com.jd.interact.center.client.api.common.param.Results","success":true}