{
   "PointExSku" : 0,
   "browse" : "WeiXin",
   "discount" : "0.00",
   "env" : 1,
   "errMsg" : "",
   "hasMemPoint" : 1,
   "hasPin" : 0,
   "iRet" : 0,
   "lmVender" : 0,
   "login" : 0,
   "logoUrl" : "//img11.360buyimg.com/cms/jfs/t28192/249/530736556/3740/cb0fb3c0/5bf6161eN836e2fd2.jpg",
   "memLeveRuleListJson" : [],
   "member" : 0,
   "memberLevel" : 0,
   "memberPoints" : 0,
   "memberTradeCount" : 0,
   "merberTradeAmount" : "0.00",
   "openVip" : 1,
   "pointExCoupon" : 0,
   "shopId" : 1000129443,
   "shopLatestSignUrl" : "//img13.360buyimg.com/cms/jfs/t1/15541/32/12567/159915/5cab07c0Ef8bdc171/c16f574aab4dc55a.jpg",
   "shopName" : "玛汀露丝（Matin Rosie）京东自营旗舰店",
   "time" : 1613557427,
   "totalScore" : "",
   "venderId" : 1000129443
}
