{
   "PointExSku" : 0,
   "browse" : "WeiXin",
   "discount" : "0.00",
   "env" : 1,
   "errMsg" : "",
   "hasMemPoint" : 0,
   "hasPin" : 0,
   "iRet" : 0,
   "lmVender" : 0,
   "login" : 0,
   "logoUrl" : "//img30.360buyimg.com/popshop/jfs/t7318/121/3488804059/5310/5d2f9f8a/59e07e94Ndf63141d.jpg",
   "memLeveRuleListJson" : [
      {
         "discount" : "9.90",
         "grade" : "1",
         "gradeName" : "一星会员",
         "maxOrderCount" : "5",
         "maxOrderPrice" : "500",
         "minOrderCount" : "0",
         "minOrderPrice" : "0",
         "multiple" : ""
      },
      {
         "discount" : "9.80",
         "grade" : "2",
         "gradeName" : "二星会员",
         "maxOrderCount" : "10",
         "maxOrderPrice" : "1000",
         "minOrderCount" : "5",
         "minOrderPrice" : "500",
         "multiple" : ""
      },
      {
         "discount" : "9.50",
         "grade" : "3",
         "gradeName" : "三星会员",
         "maxOrderCount" : "200",
         "maxOrderPrice" : "3000",
         "minOrderCount" : "10",
         "minOrderPrice" : "1000",
         "multiple" : ""
      },
      {
         "discount" : "9.00",
         "grade" : "4",
         "gradeName" : "四星会员",
         "maxOrderCount" : "30000",
         "maxOrderPrice" : "1000000",
         "minOrderCount" : "200",
         "minOrderPrice" : "3000",
         "multiple" : ""
      },
      {
         "discount" : "8.80",
         "grade" : "5",
         "gradeName" : "五星会员",
         "maxOrderCount" : "2147483647",
         "maxOrderPrice" : "92233720368547758.07",
         "minOrderCount" : "30000",
         "minOrderPrice" : "1000000",
         "multiple" : ""
      }
   ],
   "member" : 0,
   "memberLevel" : 0,
   "memberPoints" : 0,
   "memberTradeCount" : 0,
   "merberTradeAmount" : "0.00",
   "openVip" : 1,
   "pointExCoupon" : 0,
   "shopId" : 720799,
   "shopLatestSignUrl" : "//img10.360buyimg.com/cms/jfs/t21022/178/549440389/78007/45b7e568/5b11180bN4df75005.jpg",
   "shopName" : "若饭旗舰店",
   "time" : 1613561274,
   "totalScore" : "",
   "venderId" : 724715
}
