{
   "PointExSku" : 0,
   "browse" : "WeiXin",
   "discount" : "0.00",
   "env" : 1,
   "errMsg" : "",
   "hasMemPoint" : 0,
   "hasPin" : 0,
   "iRet" : 0,
   "lmVender" : 0,
   "login" : 0,
   "logoUrl" : "//img30.360buyimg.com/popshop/jfs/t3439/50/1146717907/31071/af748865/581d752eNf1cb3c3d.jpg",
   "memLeveRuleListJson" : [],
   "member" : 0,
   "memberLevel" : 0,
   "memberPoints" : 0,
   "memberTradeCount" : 0,
   "merberTradeAmount" : "0.00",
   "openVip" : 1,
   "pointExCoupon" : 0,
   "shopId" : 615083,
   "shopLatestSignUrl" : "//img11.360buyimg.com/cms/jfs/t1/7340/17/1821/115423/5bcff958E3e5bca82/d5c15ee9a6cab85e.jpg",
   "shopName" : "谦德个护专营店",
   "time" : 1613556048,
   "totalScore" : "",
   "venderId" : 621974
}
