{
   "PointExSku" : 0,
   "browse" : "WeiXin",
   "discount" : "0.00",
   "env" : 1,
   "errMsg" : "",
   "hasMemPoint" : 0,
   "hasPin" : 0,
   "iRet" : 0,
   "lmVender" : 0,
   "login" : 0,
   "logoUrl" : "//img10.360buyimg.com/cms/jfs/t1/53082/8/6060/7109/5d39c619E2a5bd090/7b76ac0dd59196db.png",
   "memLeveRuleListJson" : [],
   "member" : 0,
   "memberLevel" : 0,
   "memberPoints" : 0,
   "memberTradeCount" : 0,
   "merberTradeAmount" : "0.00",
   "openVip" : 0,
   "pointExCoupon" : 0,
   "shopId" : 10073381,
   "shopLatestSignUrl" : "//img11.360buyimg.com/cms/jfs/t1/41423/11/10283/34766/5d39c6a5E6ac8582b/0313417d80e91cd1.jpg",
   "shopName" : "槿韵轩家装建材专营店",
   "time" : 1613558192,
   "totalScore" : "",
   "venderId" : 10210042
}
