{
   "PointExSku" : 0,
   "browse" : "WeiXin",
   "discount" : "0.00",
   "env" : 1,
   "errMsg" : "",
   "hasMemPoint" : 0,
   "hasPin" : 0,
   "iRet" : 0,
   "lmVender" : 0,
   "login" : 0,
   "logoUrl" : "//img12.360buyimg.com/cms/jfs/t1/89271/4/5024/8600/5dea2568Ec3a3fa95/d2cb045518e744f9.jpg",
   "memLeveRuleListJson" : [],
   "member" : 0,
   "memberLevel" : 0,
   "memberPoints" : 0,
   "memberTradeCount" : 0,
   "merberTradeAmount" : "0.00",
   "openVip" : 1,
   "pointExCoupon" : 0,
   "shopId" : 10130837,
   "shopLatestSignUrl" : "//img10.360buyimg.com/cms/jfs/t1/109570/12/4088/104840/5e1833baE7a77dac6/a6b0722f9b1d5385.jpg",
   "shopName" : "策乐鞋类官方旗舰店",
   "time" : 1613563015,
   "totalScore" : "",
   "venderId" : 10266947
}
