{
   "PointExSku" : 0,
   "browse" : "WeiXin",
   "discount" : "0.00",
   "env" : 1,
   "errMsg" : "",
   "hasMemPoint" : 1,
   "hasPin" : 0,
   "iRet" : 0,
   "lmVender" : 0,
   "login" : 0,
   "logoUrl" : "//img13.360buyimg.com/cms/jfs/t1/140197/38/18850/8345/5fdb28b0E81422824/1f096192aaa9d609.jpg",
   "memLeveRuleListJson" : [],
   "member" : 0,
   "memberLevel" : 0,
   "memberPoints" : 0,
   "memberTradeCount" : 0,
   "merberTradeAmount" : "0.00",
   "openVip" : 1,
   "pointExCoupon" : 0,
   "shopId" : 10381414,
   "shopLatestSignUrl" : "//img10.360buyimg.com/cms/jfs/t1/141574/9/18713/51037/5fdb3275E8f51f258/36f657d5f4c961e9.jpg",
   "shopName" : "极男旗舰店",
   "time" : 1613558978,
   "totalScore" : "",
   "venderId" : 10599311
}
