{
   "PointExSku" : 0,
   "browse" : "WeiXin",
   "discount" : "0.00",
   "env" : 1,
   "errMsg" : "",
   "hasMemPoint" : 1,
   "hasPin" : 0,
   "iRet" : 0,
   "lmVender" : 0,
   "login" : 0,
   "logoUrl" : "//img12.360buyimg.com/jshopm/jfs/t5707/153/5800114580/30079/d6855d55/596328baN107a2d7f.jpg",
   "memLeveRuleListJson" : [],
   "member" : 0,
   "memberLevel" : 0,
   "memberPoints" : 0,
   "memberTradeCount" : 0,
   "merberTradeAmount" : "0.00",
   "openVip" : 1,
   "pointExCoupon" : 0,
   "shopId" : 160366,
   "shopLatestSignUrl" : "//img13.360buyimg.com/cms/jfs/t1/99011/33/18284/252075/5e948236Ef51a6a51/257981021ff4543f.jpg",
   "shopName" : "柔岚车品专营店",
   "time" : 1613555806,
   "totalScore" : "",
   "venderId" : 165874
}
