{
   "PointExSku" : 0,
   "browse" : "WeiXin",
   "discount" : "0.00",
   "env" : 1,
   "errMsg" : "",
   "hasMemPoint" : 0,
   "hasPin" : 0,
   "iRet" : 0,
   "lmVender" : 0,
   "login" : 0,
   "logoUrl" : "//img30.360buyimg.com/popshop/jfs/t1/55197/38/6432/3422/5d3fa202E7eeff12b/0567ccdf474c0e5b.jpg",
   "memLeveRuleListJson" : [],
   "member" : 0,
   "memberLevel" : 0,
   "memberPoints" : 0,
   "memberTradeCount" : 0,
   "merberTradeAmount" : "0.00",
   "openVip" : 0,
   "pointExCoupon" : 0,
   "shopId" : 10068244,
   "shopLatestSignUrl" : "//img11.360buyimg.com/cms/jfs/t1/49505/5/7126/159648/5d4d4dc9E979f5951/50a2ca159487c1c1.jpg",
   "shopName" : "京北家装建材专营店",
   "time" : 1613554969,
   "totalScore" : "",
   "venderId" : 10204444
}
