{
   "PointExSku" : 0,
   "browse" : "WeiXin",
   "discount" : "0.00",
   "env" : 1,
   "errMsg" : "",
   "hasMemPoint" : 0,
   "hasPin" : 0,
   "iRet" : 0,
   "lmVender" : 0,
   "login" : 0,
   "logoUrl" : "//img30.360buyimg.com/popshop/jfs/t1/111946/38/4635/14573/5eaf9771Ee43a688a/fc36697c38ee0531.jpg",
   "memLeveRuleListJson" : [],
   "member" : 0,
   "memberLevel" : 0,
   "memberPoints" : 0,
   "memberTradeCount" : 0,
   "merberTradeAmount" : "0.00",
   "openVip" : 0,
   "pointExCoupon" : 0,
   "shopId" : 10197546,
   "shopLatestSignUrl" : "//img10.360buyimg.com/cms/jfs/t1/118707/25/4737/62877/5eafa0e6E93bdee43/69ad62cd8567914c.jpg",
   "shopName" : "沃之沃凡铭专卖店",
   "time" : 1613558534,
   "totalScore" : "",
   "venderId" : 10343083
}
