{
   "PointExSku" : 0,
   "browse" : "WeiXin",
   "discount" : "0.00",
   "env" : 1,
   "errMsg" : "",
   "hasMemPoint" : 0,
   "hasPin" : 0,
   "iRet" : 0,
   "lmVender" : 0,
   "login" : 0,
   "logoUrl" : "//img11.360buyimg.com/cms/jfs/t1/94448/14/3214/4110/5dddcc04E76f6b02a/e1355ec7316be55b.jpg",
   "memLeveRuleListJson" : [],
   "member" : 0,
   "memberLevel" : 0,
   "memberPoints" : 0,
   "memberTradeCount" : 0,
   "merberTradeAmount" : "0.00",
   "openVip" : 0,
   "pointExCoupon" : 0,
   "shopId" : 1000302141,
   "shopLatestSignUrl" : "//img14.360buyimg.com/cms/jfs/t1/96187/9/3136/99101/5dddcc87Ecf531ac4/638096a6496e91d4.jpg",
   "shopName" : "圣邦工业品京东自营专区",
   "time" : 1613554607,
   "totalScore" : "",
   "venderId" : 1000302141
}
