{
   "PointExSku" : 0,
   "browse" : "WeiXin",
   "discount" : "0.00",
   "env" : 1,
   "errMsg" : "",
   "hasMemPoint" : 1,
   "hasPin" : 0,
   "iRet" : 0,
   "lmVender" : 0,
   "login" : 0,
   "logoUrl" : "//img12.360buyimg.com/cms/jfs/t1/44698/39/5295/21109/5d2d20f5Ea58635ce/7ee73feab2f88e31.jpg",
   "memLeveRuleListJson" : [],
   "member" : 0,
   "memberLevel" : 0,
   "memberPoints" : 0,
   "memberTradeCount" : 0,
   "merberTradeAmount" : "0.00",
   "openVip" : 1,
   "pointExCoupon" : 0,
   "shopId" : 853456,
   "shopLatestSignUrl" : "//img12.360buyimg.com/cms/jfs/t1/32937/35/14107/348780/5cbc5bc6Eea4d1558/c47b69ef4b3963c2.jpg",
   "shopName" : "比博欧官方旗舰店",
   "time" : 1613554657,
   "totalScore" : "",
   "venderId" : 10016502
}
