{
   "PointExSku" : 0,
   "browse" : "WeiXin",
   "discount" : "0.00",
   "env" : 1,
   "errMsg" : "",
   "hasMemPoint" : 0,
   "hasPin" : 0,
   "iRet" : 0,
   "lmVender" : 0,
   "login" : 0,
   "logoUrl" : "//img10.360buyimg.com/cms/jfs/t1/158646/7/452/8557/5feaf261Edb4301cf/f8722bd2ea4018e1.jpg",
   "memLeveRuleListJson" : [
      {
         "discount" : "9.50",
         "grade" : "1",
         "gradeName" : "一星会员",
         "maxOrderCount" : "1",
         "maxOrderPrice" : "100",
         "minOrderCount" : "0",
         "minOrderPrice" : "0",
         "multiple" : ""
      },
      {
         "discount" : "9.20",
         "grade" : "2",
         "gradeName" : "二星会员",
         "maxOrderCount" : "2",
         "maxOrderPrice" : "300",
         "minOrderCount" : "1",
         "minOrderPrice" : "100",
         "multiple" : ""
      },
      {
         "discount" : "9.00",
         "grade" : "3",
         "gradeName" : "三星会员",
         "maxOrderCount" : "3",
         "maxOrderPrice" : "800",
         "minOrderCount" : "2",
         "minOrderPrice" : "300",
         "multiple" : ""
      },
      {
         "discount" : "8.60",
         "grade" : "4",
         "gradeName" : "四星会员",
         "maxOrderCount" : "2147483647",
         "maxOrderPrice" : "92233720368547758.07",
         "minOrderCount" : "3",
         "minOrderPrice" : "800",
         "multiple" : ""
      }
   ],
   "member" : 0,
   "memberLevel" : 0,
   "memberPoints" : 0,
   "memberTradeCount" : 0,
   "merberTradeAmount" : "0.00",
   "openVip" : 1,
   "pointExCoupon" : 0,
   "shopId" : 10266065,
   "shopLatestSignUrl" : "//img12.360buyimg.com/cms/jfs/t1/150342/31/13824/116376/5feaf317E361f2ebc/1547da5972a8f694.jpg",
   "shopName" : "喜呀医疗器械专营店",
   "time" : 1613555353,
   "totalScore" : "",
   "venderId" : 10413192
}
