{
   "PointExSku" : 0,
   "browse" : "WeiXin",
   "discount" : "0.00",
   "env" : 1,
   "errMsg" : "",
   "hasMemPoint" : 0,
   "hasPin" : 0,
   "iRet" : 0,
   "lmVender" : 0,
   "login" : 0,
   "logoUrl" : "//img30.360buyimg.com/popshop/jfs/t1/125942/17/5103/9775/5eeb55cfE953d9b53/b29c1c40b0b764ed.png",
   "memLeveRuleListJson" : [],
   "member" : 0,
   "memberLevel" : 0,
   "memberPoints" : 0,
   "memberTradeCount" : 0,
   "merberTradeAmount" : "0.00",
   "openVip" : 1,
   "pointExCoupon" : 0,
   "shopId" : 10199064,
   "shopLatestSignUrl" : "//img14.360buyimg.com/cms/jfs/t1/155018/27/1466/214150/5f7ae423E8ff94363/f3788ac48e4f6075.jpg",
   "shopName" : "DAFY运动户外旗舰店",
   "time" : 1613563212,
   "totalScore" : "",
   "venderId" : 10322745
}
