{
   "PointExSku" : 0,
   "browse" : "WeiXin",
   "discount" : "0.00",
   "env" : 1,
   "errMsg" : "",
   "hasMemPoint" : 0,
   "hasPin" : 0,
   "iRet" : 0,
   "lmVender" : 0,
   "login" : 0,
   "logoUrl" : "//img11.360buyimg.com/cms/jfs/t1/146185/31/11944/5038/5f92d4f3Ed613f6bc/c6298d98d0ac8f0e.jpg",
   "memLeveRuleListJson" : [],
   "member" : 0,
   "memberLevel" : 0,
   "memberPoints" : 0,
   "memberTradeCount" : 0,
   "merberTradeAmount" : "0.00",
   "openVip" : 0,
   "pointExCoupon" : 0,
   "shopId" : 10330390,
   "shopLatestSignUrl" : "//img11.360buyimg.com/cms/jfs/t1/144428/1/11906/63596/5f92d624Ed43410f2/0aef5b7d1d7f7ebf.jpg",
   "shopName" : "蓝鹰官方旗舰店",
   "time" : 1613563687,
   "totalScore" : "",
   "venderId" : 10542191
}
