{
   "PointExSku" : 0,
   "browse" : "WeiXin",
   "discount" : "0.00",
   "env" : 1,
   "errMsg" : "",
   "hasMemPoint" : 0,
   "hasPin" : 0,
   "iRet" : 0,
   "lmVender" : 0,
   "login" : 0,
   "logoUrl" : "//img30.360buyimg.com/popshop/jfs/t1/140731/18/1848/12065/5efc1e71E2932e5f2/964c00530466aff3.jpg",
   "memLeveRuleListJson" : [],
   "member" : 0,
   "memberLevel" : 0,
   "memberPoints" : 0,
   "memberTradeCount" : 0,
   "merberTradeAmount" : "0.00",
   "openVip" : 1,
   "pointExCoupon" : 0,
   "shopId" : 1000335882,
   "shopLatestSignUrl" : "//img14.360buyimg.com/cms/jfs/t1/118844/25/11287/78759/5efd7d6dEe2abf8fd/dd181ed2df339972.jpg",
   "shopName" : "可立仕（cleace）京东自营旗舰店",
   "time" : 1613557687,
   "totalScore" : "",
   "venderId" : 1000335882
}
