{
   "PointExSku" : 0,
   "browse" : "WeiXin",
   "discount" : "0.00",
   "env" : 1,
   "errMsg" : "",
   "hasMemPoint" : 0,
   "hasPin" : 0,
   "iRet" : 0,
   "lmVender" : 0,
   "login" : 0,
   "logoUrl" : "//img10.360buyimg.com/cms/jfs/t1/143361/3/12093/6413/5f963d29E7ea6569d/95c101e86aec4e90.jpg",
   "memLeveRuleListJson" : [],
   "member" : 0,
   "memberLevel" : 0,
   "memberPoints" : 0,
   "memberTradeCount" : 0,
   "merberTradeAmount" : "0.00",
   "openVip" : 1,
   "pointExCoupon" : 0,
   "shopId" : 983762,
   "shopLatestSignUrl" : "//img10.360buyimg.com/cms/jfs/t1/85142/37/7338/238955/5df997dcEe582a2ad/31591c9b53e77e5e.jpg",
   "shopName" : "珍行足衣京东自营旗舰店",
   "time" : 1613562619,
   "totalScore" : "",
   "venderId" : 10135237
}
