{
   "PointExSku" : 0,
   "browse" : "WeiXin",
   "discount" : "0.00",
   "env" : 1,
   "errMsg" : "",
   "hasMemPoint" : 0,
   "hasPin" : 0,
   "iRet" : 0,
   "lmVender" : 0,
   "login" : 0,
   "logoUrl" : "//img10.360buyimg.com/cms/jfs/t1/103232/22/15000/10336/5e6af9b2E80a3a248/a4037670a400837c.jpg",
   "memLeveRuleListJson" : [],
   "member" : 0,
   "memberLevel" : 0,
   "memberPoints" : 0,
   "memberTradeCount" : 0,
   "merberTradeAmount" : "0.00",
   "openVip" : 0,
   "pointExCoupon" : 0,
   "shopId" : 10054674,
   "shopLatestSignUrl" : "//img14.360buyimg.com/cms/jfs/t1/95806/15/14912/182678/5e6afb42E19186b4b/6f3e5ae2ebfac9b4.png",
   "shopName" : "斯比来鞋靴旗舰店",
   "time" : 1613562712,
   "totalScore" : "",
   "venderId" : 10190042
}
