{"code":200,"data":{"userActivityStatus":1,"continuePrizeRuleList":[{"level":3,"prizeList":[{"discount":10.00,"type":6,"number":10000,"budgetNum":100000,"userPirzeStatus":1,"class":"com.jd.interact.center.client.api.user.domain.InteractUserPrize","status":2}],"signType":1,"days":3,"class":"com.jd.interact.center.client.api.color.domain.sign.ShopSignInteractUserPrizeRule"}],"activityStatus":2,"activityName":"签到送积分","venderId":1000323646,"startTime":1612108800000,"endTime":1614527999000,"id":10250050,"class":"com.jd.interact.center.client.api.color.domain.sign.ShopSignActivity","prizeRuleList":[{"level":0,"prizeList":[{"discount":2.00,"type":6,"number":10000,"budgetNum":20000,"userPirzeStatus":1,"class":"com.jd.interact.center.client.api.user.domain.InteractUserPrize","status":2}],"class":"com.jd.interact.center.client.api.color.domain.sign.ShopSignInteractUserPrizeRule"}]},"class":"com.jd.interact.center.client.api.common.param.Results","success":true}