{
   "PointExSku" : 0,
   "browse" : "WeiXin",
   "discount" : "0.00",
   "env" : 1,
   "errMsg" : "",
   "hasMemPoint" : 0,
   "hasPin" : 0,
   "iRet" : 0,
   "lmVender" : 0,
   "login" : 0,
   "logoUrl" : "//img12.360buyimg.com/cms/jfs/t1/122203/38/18241/10362/5fae2fabE9385461c/ad98fa84a99bc4ec.png",
   "memLeveRuleListJson" : [],
   "member" : 0,
   "memberLevel" : 0,
   "memberPoints" : 0,
   "memberTradeCount" : 0,
   "merberTradeAmount" : "0.00",
   "openVip" : 0,
   "pointExCoupon" : 0,
   "shopId" : 159992,
   "shopLatestSignUrl" : "//img11.360buyimg.com/cms/jfs/t1/142553/15/14276/91164/5fae3169E5e2d752c/4d3cf571340f4c2c.jpg",
   "shopName" : "火迪鸟户外专营店",
   "time" : 1613564056,
   "totalScore" : "",
   "venderId" : 165486
}
