{
   "PointExSku" : 0,
   "browse" : "WeiXin",
   "discount" : "0.00",
   "env" : 1,
   "errMsg" : "",
   "hasMemPoint" : 0,
   "hasPin" : 0,
   "iRet" : 0,
   "lmVender" : 0,
   "login" : 0,
   "logoUrl" : "//img10.360buyimg.com/cms/jfs/t1/118221/35/12742/2873/5f154e3fE2394cd10/ae9913f45feecbc7.png",
   "memLeveRuleListJson" : [],
   "member" : 0,
   "memberLevel" : 0,
   "memberPoints" : 0,
   "memberTradeCount" : 0,
   "merberTradeAmount" : "0.00",
   "openVip" : 0,
   "pointExCoupon" : 0,
   "shopId" : 10213703,
   "shopLatestSignUrl" : "//img13.360buyimg.com/cms/jfs/t1/128639/33/7494/132114/5f1550e0Ea160f4b0/a2f202b9eab75bdb.jpg",
   "shopName" : "德米医疗器械专营店",
   "time" : 1613555241,
   "totalScore" : "",
   "venderId" : 10360624
}
