{
   "PointExSku" : 0,
   "browse" : "WeiXin",
   "discount" : "0.00",
   "env" : 1,
   "errMsg" : "",
   "hasMemPoint" : 1,
   "hasPin" : 0,
   "iRet" : 0,
   "lmVender" : 0,
   "login" : 0,
   "logoUrl" : "//img11.360buyimg.com/cms/jfs/t1/83039/16/15301/4008/5dcd26b7Ec9d9e854/283292bd7938151a.jpg",
   "memLeveRuleListJson" : [],
   "member" : 0,
   "memberLevel" : 0,
   "memberPoints" : 0,
   "memberTradeCount" : 0,
   "merberTradeAmount" : "0.00",
   "openVip" : 1,
   "pointExCoupon" : 0,
   "shopId" : 101321,
   "shopLatestSignUrl" : "//img10.360buyimg.com/cms/jfs/t1/73714/35/15205/29746/5dcd2732Ec5369934/e3d9b8cf3acdd791.jpg",
   "shopName" : "真丽斯官方旗舰店",
   "time" : 1613558411,
   "totalScore" : "",
   "venderId" : 102968
}
