{
   "PointExSku" : 0,
   "browse" : "WeiXin",
   "discount" : "0.00",
   "env" : 1,
   "errMsg" : "",
   "hasMemPoint" : 0,
   "hasPin" : 0,
   "iRet" : 0,
   "lmVender" : 0,
   "login" : 0,
   "logoUrl" : "//img14.360buyimg.com/cms/jfs/t1/137932/28/8058/35295/5f58bf6eEfb7ea975/0ce2f253b8ada3ad.jpg",
   "memLeveRuleListJson" : [],
   "member" : 0,
   "memberLevel" : 0,
   "memberPoints" : 0,
   "memberTradeCount" : 0,
   "merberTradeAmount" : "0.00",
   "openVip" : 0,
   "pointExCoupon" : 0,
   "shopId" : 10020036,
   "shopLatestSignUrl" : "//img10.360buyimg.com/cms/jfs/t1/128934/30/12206/141478/5f58c1f1Eab7f6abe/b1a9fb1d4c91efcb.jpg",
   "shopName" : "圣彬霸服饰旗舰店",
   "time" : 1613562654,
   "totalScore" : "",
   "venderId" : 10154817
}
