{
   "PointExSku" : 0,
   "browse" : "WeiXin",
   "discount" : "0.00",
   "env" : 1,
   "errMsg" : "",
   "hasMemPoint" : 1,
   "hasPin" : 0,
   "iRet" : 0,
   "lmVender" : 0,
   "login" : 0,
   "logoUrl" : "//img11.360buyimg.com/cms/jfs/t1/28698/16/15475/4064/5cb0a76dEe2ef8d4f/65e2e21709904891.png",
   "memLeveRuleListJson" : [],
   "member" : 0,
   "memberLevel" : 0,
   "memberPoints" : 0,
   "memberTradeCount" : 0,
   "merberTradeAmount" : "0.00",
   "openVip" : 1,
   "pointExCoupon" : 0,
   "shopId" : 1000093043,
   "shopLatestSignUrl" : "//img10.360buyimg.com/cms/jfs/t1/16104/17/15671/97181/5cb0a78eE60764f31/354c3fa9a6c2f262.jpg",
   "shopName" : "Keep京东自营旗舰店",
   "time" : 1613562129,
   "totalScore" : "",
   "venderId" : 1000093043
}
