{
   "PointExSku" : 0,
   "browse" : "WeiXin",
   "discount" : "0.00",
   "env" : 1,
   "errMsg" : "",
   "hasMemPoint" : 1,
   "hasPin" : 0,
   "iRet" : 0,
   "lmVender" : 0,
   "login" : 0,
   "logoUrl" : "//img13.360buyimg.com/cms/jfs/t1/106288/22/17904/8315/5e8c3f5fEf5ef3c43/04731a3731467232.gif",
   "memLeveRuleListJson" : [],
   "member" : 0,
   "memberLevel" : 0,
   "memberPoints" : 0,
   "memberTradeCount" : 0,
   "merberTradeAmount" : "0.00",
   "openVip" : 1,
   "pointExCoupon" : 0,
   "shopId" : 1000078086,
   "shopLatestSignUrl" : "//img10.360buyimg.com/cms/jfs/t1/101644/1/17813/126982/5e8c1a3eEade2f6dd/97f63bd339b5f103.jpg",
   "shopName" : "普丽普莱（Puritan&#39;s Pride）海外京东自营旗舰店",
   "time" : 1613562047,
   "totalScore" : "",
   "venderId" : 1000078086
}
