{
   "PointExSku" : 0,
   "browse" : "WeiXin",
   "discount" : "0.00",
   "env" : 1,
   "errMsg" : "",
   "hasMemPoint" : 1,
   "hasPin" : 0,
   "iRet" : 0,
   "lmVender" : 0,
   "login" : 0,
   "logoUrl" : "//img13.360buyimg.com/cms/jfs/t1/146074/4/1643/17246/5ef836d4E22295541/078437251a765bf2.jpg",
   "memLeveRuleListJson" : [],
   "member" : 0,
   "memberLevel" : 0,
   "memberPoints" : 0,
   "memberTradeCount" : 0,
   "merberTradeAmount" : "0.00",
   "openVip" : 1,
   "pointExCoupon" : 0,
   "shopId" : 665984,
   "shopLatestSignUrl" : "//img14.360buyimg.com/cms/jfs/t1/118083/17/11050/180926/5ef83a88E3ada7123/4cfd9d73e8b2e17f.jpg",
   "shopName" : "Translation Officer旗舰店",
   "time" : 1613556160,
   "totalScore" : "",
   "venderId" : 670340
}
