{
   "PointExSku" : 0,
   "browse" : "WeiXin",
   "discount" : "0.00",
   "env" : 1,
   "errMsg" : "",
   "hasMemPoint" : 0,
   "hasPin" : 0,
   "iRet" : 0,
   "lmVender" : 0,
   "login" : 0,
   "logoUrl" : "//img12.360buyimg.com/cms/jfs/t1/72132/28/16321/6405/5ddd4815E897f05f6/1972a2d3b2829fc8.jpg",
   "memLeveRuleListJson" : [],
   "member" : 0,
   "memberLevel" : 0,
   "memberPoints" : 0,
   "memberTradeCount" : 0,
   "merberTradeAmount" : "0.00",
   "openVip" : 0,
   "pointExCoupon" : 0,
   "shopId" : 10097428,
   "shopLatestSignUrl" : "//img12.360buyimg.com/cms/jfs/t1/102810/21/4015/4752/5de3fd13E2c0270b9/70d780ef7fc89f3b.jpg",
   "shopName" : "柒喵喵美妆专营店",
   "time" : 1613558266,
   "totalScore" : "",
   "venderId" : 10235218
}
