{
   "PointExSku" : 0,
   "browse" : "WeiXin",
   "discount" : "0.00",
   "env" : 1,
   "errMsg" : "",
   "hasMemPoint" : 0,
   "hasPin" : 0,
   "iRet" : 0,
   "lmVender" : 0,
   "login" : 0,
   "logoUrl" : "//img12.360buyimg.com/jshopm/jfs/t160/67/2605583417/23026/5b8368c7/53d22812N3d08f072.jpg",
   "memLeveRuleListJson" : [],
   "member" : 0,
   "memberLevel" : 0,
   "memberPoints" : 0,
   "memberTradeCount" : 0,
   "merberTradeAmount" : "0.00",
   "openVip" : 1,
   "pointExCoupon" : 0,
   "shopId" : 82302,
   "shopLatestSignUrl" : "//img12.360buyimg.com/jshopm/jfs/t7792/140/4146876609/77247/7e4c1164/59ceffb2N432199da.jpg",
   "shopName" : "酷丽莱家居用品专营店",
   "time" : 1613561467,
   "totalScore" : "",
   "venderId" : 85357
}
