{
   "PointExSku" : 0,
   "browse" : "WeiXin",
   "discount" : "0.00",
   "env" : 1,
   "errMsg" : "",
   "hasMemPoint" : 1,
   "hasPin" : 0,
   "iRet" : 0,
   "lmVender" : 0,
   "login" : 0,
   "logoUrl" : "//img14.360buyimg.com/cms/jfs/t1/144336/12/6101/6995/5f3f4aa9Ed28078c8/735f432db37dfb7d.jpg",
   "memLeveRuleListJson" : [],
   "member" : 0,
   "memberLevel" : 0,
   "memberPoints" : 0,
   "memberTradeCount" : 0,
   "merberTradeAmount" : "0.00",
   "openVip" : 1,
   "pointExCoupon" : 0,
   "shopId" : 1000159162,
   "shopLatestSignUrl" : "//img12.360buyimg.com/cms/jfs/t1/131255/17/15724/5569/5fabab13Ee582c01c/8fe8328221abdab8.jpg",
   "shopName" : "宠迪雅（petdior）京东自营旗舰店",
   "time" : 1613557476,
   "totalScore" : "",
   "venderId" : 1000159162
}
