{
   "PointExSku" : 0,
   "browse" : "WeiXin",
   "discount" : "0.00",
   "env" : 1,
   "errMsg" : "",
   "hasMemPoint" : 1,
   "hasPin" : 0,
   "iRet" : 0,
   "lmVender" : 0,
   "login" : 0,
   "logoUrl" : "//img30.360buyimg.com/popshop/jfs/t1/17673/11/9796/7607/5c8208a9E13912538/036fd3978858844b.jpg",
   "memLeveRuleListJson" : [],
   "member" : 0,
   "memberLevel" : 0,
   "memberPoints" : 0,
   "memberTradeCount" : 0,
   "merberTradeAmount" : "0.00",
   "openVip" : 1,
   "pointExCoupon" : 0,
   "shopId" : 957123,
   "shopLatestSignUrl" : "//img12.360buyimg.com/cms/jfs/t1/42935/32/10671/96186/5d41233cE6f39fc69/71897904eabeffa7.jpg",
   "shopName" : "aas旗舰店",
   "time" : 1613554809,
   "totalScore" : "",
   "venderId" : 10113337
}
