{
   "PointExSku" : 0,
   "browse" : "WeiXin",
   "discount" : "0.00",
   "env" : 1,
   "errMsg" : "",
   "hasMemPoint" : 0,
   "hasPin" : 0,
   "iRet" : 0,
   "lmVender" : 0,
   "login" : 0,
   "logoUrl" : "//img12.360buyimg.com/cms/jfs/t1/107765/24/16322/15278/5eb23800E2cda09c5/1957a7a0cd50f1a4.jpg",
   "memLeveRuleListJson" : [],
   "member" : 0,
   "memberLevel" : 0,
   "memberPoints" : 0,
   "memberTradeCount" : 0,
   "merberTradeAmount" : "0.00",
   "openVip" : 0,
   "pointExCoupon" : 0,
   "shopId" : 1000330785,
   "shopLatestSignUrl" : "//img14.360buyimg.com/cms/jfs/t1/113768/10/5259/213108/5eb2337fEba1c97cc/1841d12be55cdddc.jpg",
   "shopName" : "怡雪（USHINE）京东自营旗舰店",
   "time" : 1613557644,
   "totalScore" : "",
   "venderId" : 1000330785
}
