{
   "PointExSku" : 0,
   "browse" : "WeiXin",
   "discount" : "0.00",
   "env" : 1,
   "errMsg" : "",
   "hasMemPoint" : 1,
   "hasPin" : 0,
   "iRet" : 0,
   "lmVender" : 0,
   "login" : 0,
   "logoUrl" : "//img30.360buyimg.com/popshop/jfs/t700/265/1248679415/13640/2581b973/552a2fa1N7047cba5.png",
   "memLeveRuleListJson" : [],
   "member" : 0,
   "memberLevel" : 0,
   "memberPoints" : 0,
   "memberTradeCount" : 0,
   "merberTradeAmount" : "0.00",
   "openVip" : 1,
   "pointExCoupon" : 0,
   "shopId" : 127072,
   "shopLatestSignUrl" : "//img12.360buyimg.com/cms/jfs/t1/116059/12/3579/328288/5ea8fb6aE7f7926d7/826072ea30f10a61.jpg",
   "shopName" : "哆啦运动专营店",
   "time" : 1613563943,
   "totalScore" : "",
   "venderId" : 131119
}
