{
   "PointExSku" : 0,
   "browse" : "WeiXin",
   "discount" : "0.00",
   "env" : 1,
   "errMsg" : "",
   "hasMemPoint" : 1,
   "hasPin" : 0,
   "iRet" : 0,
   "lmVender" : 0,
   "login" : 0,
   "logoUrl" : "//img12.360buyimg.com/cms/jfs/t1/147645/12/6089/16209/5f3fc4bcEda130f08/52a74a8800056d4a.jpg",
   "memLeveRuleListJson" : [],
   "member" : 0,
   "memberLevel" : 0,
   "memberPoints" : 0,
   "memberTradeCount" : 0,
   "merberTradeAmount" : "0.00",
   "openVip" : 1,
   "pointExCoupon" : 0,
   "shopId" : 10182306,
   "shopLatestSignUrl" : "//img12.360buyimg.com/cms/jfs/t1/142379/11/6142/154975/5f3fc602Ead1d844e/db417dc5332ebcc1.jpg",
   "shopName" : "叶盼旗舰店",
   "time" : 1613563214,
   "totalScore" : "",
   "venderId" : 10323781
}
