{
   "PointExSku" : 0,
   "browse" : "WeiXin",
   "discount" : "0.00",
   "env" : 1,
   "errMsg" : "",
   "hasMemPoint" : 0,
   "hasPin" : 0,
   "iRet" : 0,
   "lmVender" : 0,
   "login" : 0,
   "logoUrl" : "//img30.360buyimg.com/popshop/jfs/t1/115736/20/1924/11110/5e9d1952E55be3e44/3c68dfb77c4e8c7f.jpg",
   "memLeveRuleListJson" : [],
   "member" : 0,
   "memberLevel" : 0,
   "memberPoints" : 0,
   "memberTradeCount" : 0,
   "merberTradeAmount" : "0.00",
   "openVip" : 0,
   "pointExCoupon" : 0,
   "shopId" : 10189675,
   "shopLatestSignUrl" : "//img10.360buyimg.com/cms/jfs/t1/110805/2/4702/28299/5e9e981eE6ecb40d7/f88cc13c83c6ccc1.jpg",
   "shopName" : "KAMIBAKO海外旗舰店",
   "time" : 1613558502,
   "totalScore" : "",
   "venderId" : 10334547
}
