{
   "PointExSku" : 0,
   "browse" : "WeiXin",
   "discount" : "0.00",
   "env" : 1,
   "errMsg" : "",
   "hasMemPoint" : 0,
   "hasPin" : 0,
   "iRet" : 0,
   "lmVender" : 0,
   "login" : 0,
   "logoUrl" : "//img14.360buyimg.com/cms/jfs/t1/83373/7/132/18881/5ce2bd30E4b84f13e/fb8ba54dc7c7b6d9.jpg",
   "memLeveRuleListJson" : [],
   "member" : 0,
   "memberLevel" : 0,
   "memberPoints" : 0,
   "memberTradeCount" : 0,
   "merberTradeAmount" : "0.00",
   "openVip" : 0,
   "pointExCoupon" : 0,
   "shopId" : 717346,
   "shopLatestSignUrl" : "//img14.360buyimg.com/cms/jfs/t30823/180/1533394750/2773/2afb4903/5ce2bd5aN80d5b5e9.jpg",
   "shopName" : "幻翎家纺专营店",
   "time" : 1613556357,
   "totalScore" : "",
   "venderId" : 722129
}
