{
   "PointExSku" : 0,
   "browse" : "WeiXin",
   "discount" : "0.00",
   "env" : 1,
   "errMsg" : "",
   "hasMemPoint" : 0,
   "hasPin" : 0,
   "iRet" : 0,
   "lmVender" : 0,
   "login" : 0,
   "logoUrl" : "//img14.360buyimg.com/cms/jfs/t1/128196/26/1224/4992/5ebb573dE92948e51/53e610fa07ce963d.jpg",
   "memLeveRuleListJson" : [],
   "member" : 0,
   "memberLevel" : 0,
   "memberPoints" : 0,
   "memberTradeCount" : 0,
   "merberTradeAmount" : "0.00",
   "openVip" : 1,
   "pointExCoupon" : 0,
   "shopId" : 586527,
   "shopLatestSignUrl" : "//img11.360buyimg.com/cms/jfs/t20800/165/569051197/297540/1823f7d6/5b10fea8Nfae2a78a.jpg",
   "shopName" : "山西农特产品专营店",
   "time" : 1613561121,
   "totalScore" : "",
   "venderId" : 594952
}
