{
   "PointExSku" : 0,
   "browse" : "WeiXin",
   "discount" : "0.00",
   "env" : 1,
   "errMsg" : "",
   "hasMemPoint" : 0,
   "hasPin" : 0,
   "iRet" : 0,
   "lmVender" : 0,
   "login" : 0,
   "logoUrl" : "//img12.360buyimg.com/cms/jfs/t1/111096/6/5146/10083/5eb25fe3E22511b69/181f0985c33c8842.jpg",
   "memLeveRuleListJson" : [],
   "member" : 0,
   "memberLevel" : 0,
   "memberPoints" : 0,
   "memberTradeCount" : 0,
   "merberTradeAmount" : "0.00",
   "openVip" : 0,
   "pointExCoupon" : 0,
   "shopId" : 1000003535,
   "shopLatestSignUrl" : "//img13.360buyimg.com/cms/jfs/t16642/139/2219939804/263808/39000011/5aec2ce9N891c6415.jpg",
   "shopName" : "爱华仕箱包京东自营旗舰店",
   "time" : 1613561950,
   "totalScore" : "",
   "venderId" : 1000003535
}
