{
   "PointExSku" : 0,
   "browse" : "WeiXin",
   "discount" : "0.00",
   "env" : 1,
   "errMsg" : "",
   "hasMemPoint" : 1,
   "hasPin" : 0,
   "iRet" : 0,
   "lmVender" : 0,
   "login" : 0,
   "logoUrl" : "//img30.360buyimg.com/popshop/jfs/t19855/150/963252665/38066/87796cb7/5b10aff3Nb124aeae.jpg",
   "memLeveRuleListJson" : [],
   "member" : 0,
   "memberLevel" : 0,
   "memberPoints" : 0,
   "memberTradeCount" : 0,
   "merberTradeAmount" : "0.00",
   "openVip" : 1,
   "pointExCoupon" : 0,
   "shopId" : 93768,
   "shopLatestSignUrl" : "//img14.360buyimg.com/cms/jfs/t1/51434/32/2924/317207/5d0aec7fE913b0a97/c688ae4ffdedb5f6.jpg",
   "shopName" : "潜水艇鲁明鸿专卖店",
   "time" : 1613559656,
   "totalScore" : "",
   "venderId" : 96026
}
