{
   "PointExSku" : 0,
   "browse" : "WeiXin",
   "discount" : "0.00",
   "env" : 1,
   "errMsg" : "",
   "hasMemPoint" : 0,
   "hasPin" : 0,
   "iRet" : 0,
   "lmVender" : 0,
   "login" : 0,
   "logoUrl" : "//img12.360buyimg.com/cms/jfs/t1/9817/2/6976/16595/5be2a559E8971f6bd/2d4dd3837b971753.jpg",
   "memLeveRuleListJson" : [],
   "member" : 0,
   "memberLevel" : 0,
   "memberPoints" : 0,
   "memberTradeCount" : 0,
   "merberTradeAmount" : "0.00",
   "openVip" : 0,
   "pointExCoupon" : 0,
   "shopId" : 888997,
   "shopLatestSignUrl" : "//img12.360buyimg.com/cms/jfs/t1/10234/28/2945/215425/5be2a42fE7986869e/00ac555b3bd8affe.jpg",
   "shopName" : "梨花猫官方旗舰店",
   "time" : 1613560211,
   "totalScore" : "",
   "venderId" : 10049932
}
