{
   "PointExSku" : 0,
   "browse" : "WeiXin",
   "discount" : "0.00",
   "env" : 1,
   "errMsg" : "",
   "hasMemPoint" : 1,
   "hasPin" : 0,
   "iRet" : 0,
   "lmVender" : 0,
   "login" : 0,
   "logoUrl" : "//img30.360buyimg.com/popshop/jfs/t1975/44/2717358948/22358/b3ba1b8a/56ea6e99N31d07d89.jpg",
   "memLeveRuleListJson" : [
      {
         "discount" : "9.90",
         "grade" : "1",
         "gradeName" : "一星会员",
         "maxOrderCount" : "2",
         "maxOrderPrice" : "500",
         "minOrderCount" : "0",
         "minOrderPrice" : "0",
         "multiple" : "2.0"
      },
      {
         "discount" : "9.80",
         "grade" : "2",
         "gradeName" : "二星会员",
         "maxOrderCount" : "4",
         "maxOrderPrice" : "1000",
         "minOrderCount" : "2",
         "minOrderPrice" : "500",
         "multiple" : "4.0"
      },
      {
         "discount" : "9.70",
         "grade" : "3",
         "gradeName" : "三星会员",
         "maxOrderCount" : "6",
         "maxOrderPrice" : "2500",
         "minOrderCount" : "4",
         "minOrderPrice" : "1000",
         "multiple" : "6.0"
      },
      {
         "discount" : "9.60",
         "grade" : "4",
         "gradeName" : "四星会员",
         "maxOrderCount" : "8",
         "maxOrderPrice" : "3500",
         "minOrderCount" : "6",
         "minOrderPrice" : "2500",
         "multiple" : "8.0"
      },
      {
         "discount" : "9.50",
         "grade" : "5",
         "gradeName" : "五星会员",
         "maxOrderCount" : "2147483647",
         "maxOrderPrice" : "92233720368547758.07",
         "minOrderCount" : "8",
         "minOrderPrice" : "3500",
         "multiple" : "10.0"
      }
   ],
   "member" : 0,
   "memberLevel" : 0,
   "memberPoints" : 0,
   "memberTradeCount" : 0,
   "merberTradeAmount" : "0.00",
   "openVip" : 1,
   "pointExCoupon" : 0,
   "shopId" : 119010,
   "shopLatestSignUrl" : "//img12.360buyimg.com/cms/jfs/t1/141014/12/1208/164593/5ef05cb0E5f7640a3/a53d3e15f608e948.jpg",
   "shopName" : "PLAYBOY花花公子鞋品旗舰店",
   "time" : 1613563916,
   "totalScore" : "",
   "venderId" : 122366
}
