{
   "PointExSku" : 0,
   "browse" : "WeiXin",
   "discount" : "0.00",
   "env" : 1,
   "errMsg" : "",
   "hasMemPoint" : 1,
   "hasPin" : 0,
   "iRet" : 0,
   "lmVender" : 0,
   "login" : 0,
   "logoUrl" : "//img14.360buyimg.com/cms/jfs/t1/111651/40/18152/20413/5f5f13a1E2a66f5d4/8a6921d768aa8f46.jpg",
   "memLeveRuleListJson" : [],
   "member" : 0,
   "memberLevel" : 0,
   "memberPoints" : 0,
   "memberTradeCount" : 0,
   "merberTradeAmount" : "0.00",
   "openVip" : 1,
   "pointExCoupon" : 0,
   "shopId" : 1000347101,
   "shopLatestSignUrl" : "//img13.360buyimg.com/cms/jfs/t1/126243/27/12601/130368/5f5f146cE268f8624/ec307921da719d56.jpg",
   "shopName" : "蕉下（bananaunder）户外京东自营旗舰店",
   "time" : 1613562390,
   "totalScore" : "",
   "venderId" : 1000347101
}
