{
   "PointExSku" : 0,
   "browse" : "WeiXin",
   "discount" : "0.00",
   "env" : 1,
   "errMsg" : "",
   "hasMemPoint" : 0,
   "hasPin" : 0,
   "iRet" : 0,
   "lmVender" : 0,
   "login" : 0,
   "logoUrl" : "//img30.360buyimg.com/popshop/jfs/t514/216/1405493063/10245/6bb7cd37/54d7254fN7ab1f7f9.jpg",
   "memLeveRuleListJson" : [],
   "member" : 0,
   "memberLevel" : 0,
   "memberPoints" : 0,
   "memberTradeCount" : 0,
   "merberTradeAmount" : "0.00",
   "openVip" : 0,
   "pointExCoupon" : 0,
   "shopId" : 70327,
   "shopLatestSignUrl" : "//img13.360buyimg.com/cms/jfs/t1/23078/22/8426/213456/5c750067E80ce7b72/dce0b3f6a6d32ad2.jpg",
   "shopName" : "马来西亚馆",
   "time" : 1613561299,
   "totalScore" : "",
   "venderId" : 73898
}
