{
   "PointExSku" : 0,
   "browse" : "WeiXin",
   "discount" : "0.00",
   "env" : 1,
   "errMsg" : "",
   "hasMemPoint" : 1,
   "hasPin" : 0,
   "iRet" : 0,
   "lmVender" : 0,
   "login" : 0,
   "logoUrl" : "//img11.360buyimg.com/cms/jfs/t1/164959/27/1648/10739/5ff82b9bE80ff048c/8103b22aa27fb78c.jpg",
   "memLeveRuleListJson" : [],
   "member" : 0,
   "memberLevel" : 0,
   "memberPoints" : 0,
   "memberTradeCount" : 0,
   "merberTradeAmount" : "0.00",
   "openVip" : 1,
   "pointExCoupon" : 0,
   "shopId" : 10387699,
   "shopLatestSignUrl" : "//img11.360buyimg.com/cms/jfs/t1/169433/17/1558/363758/5ff7b0c8Ea4b12e97/b98b65655156e299.jpg",
   "shopName" : "衣恋集团官方旗舰店",
   "time" : 1613563816,
   "totalScore" : "",
   "venderId" : 10612327
}
