{
   "PointExSku" : 0,
   "browse" : "WeiXin",
   "discount" : "0.00",
   "env" : 1,
   "errMsg" : "",
   "hasMemPoint" : 1,
   "hasPin" : 0,
   "iRet" : 0,
   "lmVender" : 0,
   "login" : 0,
   "logoUrl" : "//img10.360buyimg.com/cms/jfs/t1/35558/2/4146/12108/5cbacf4aEd7e9f7fa/56b053cf06c66419.jpg",
   "memLeveRuleListJson" : [],
   "member" : 0,
   "memberLevel" : 0,
   "memberPoints" : 0,
   "memberTradeCount" : 0,
   "merberTradeAmount" : "0.00",
   "openVip" : 1,
   "pointExCoupon" : 0,
   "shopId" : 717957,
   "shopLatestSignUrl" : "//img13.360buyimg.com/cms/jfs/t1/98484/16/291/478207/5daabe8eE486429dc/17aacc93232a215a.jpg",
   "shopName" : "盛阳康个护健康旗舰店",
   "time" : 1613556359,
   "totalScore" : "",
   "venderId" : 722708
}
