{
   "PointExSku" : 0,
   "browse" : "WeiXin",
   "discount" : "0.00",
   "env" : 1,
   "errMsg" : "",
   "hasMemPoint" : 1,
   "hasPin" : 0,
   "iRet" : 0,
   "lmVender" : 0,
   "login" : 0,
   "logoUrl" : "//img10.360buyimg.com/cms/jfs/t1/85418/29/14792/24150/5e6c4501Ef3b6ffaf/204e1df0e6a2dd1a.jpg",
   "memLeveRuleListJson" : [],
   "member" : 0,
   "memberLevel" : 0,
   "memberPoints" : 0,
   "memberTradeCount" : 0,
   "merberTradeAmount" : "0.00",
   "openVip" : 1,
   "pointExCoupon" : 0,
   "shopId" : 22511,
   "shopLatestSignUrl" : "//img13.360buyimg.com/cms/jfs/t1/99519/31/14908/19155/5e6c4166Eb0ff5f1f/212b63836cfe41cc.jpg",
   "shopName" : "百合康旗舰店",
   "time" : 1613561082,
   "totalScore" : "",
   "venderId" : 23107
}
