{
   "PointExSku" : 0,
   "browse" : "WeiXin",
   "discount" : "0.00",
   "env" : 1,
   "errMsg" : "",
   "hasMemPoint" : 0,
   "hasPin" : 0,
   "iRet" : 0,
   "lmVender" : 0,
   "login" : 0,
   "logoUrl" : "//img10.360buyimg.com/cms/jfs/t19915/185/1425194805/5393/13b9a345/5b470914Na96774f0.jpg",
   "memLeveRuleListJson" : [],
   "member" : 0,
   "memberLevel" : 0,
   "memberPoints" : 0,
   "memberTradeCount" : 0,
   "merberTradeAmount" : "0.00",
   "openVip" : 1,
   "pointExCoupon" : 0,
   "shopId" : 1000105601,
   "shopLatestSignUrl" : "//img14.360buyimg.com/cms/jfs/t23260/295/869768557/281536/c7b6cad3/5b4708a5N1e3dfb52.jpg",
   "shopName" : "暴走的萝莉（sylphlike loli）京东自营旗舰店",
   "time" : 1613562189,
   "totalScore" : "",
   "venderId" : 1000105601
}
