{
   "PointExSku" : 0,
   "browse" : "WeiXin",
   "discount" : "0.00",
   "env" : 1,
   "errMsg" : "",
   "hasMemPoint" : 1,
   "hasPin" : 0,
   "iRet" : 0,
   "lmVender" : 0,
   "login" : 0,
   "logoUrl" : "//img30.360buyimg.com/popshop/jfs/t15799/180/2007941838/8342/2678a24e/5a72c29fN75459ad7.jpg",
   "memLeveRuleListJson" : [],
   "member" : 0,
   "memberLevel" : 0,
   "memberPoints" : 0,
   "memberTradeCount" : 0,
   "merberTradeAmount" : "0.00",
   "openVip" : 1,
   "pointExCoupon" : 0,
   "shopId" : 72777,
   "shopLatestSignUrl" : "//img11.360buyimg.com/cms/jfs/t1/118674/29/2375/23586/5ea252e8E0c03c756/17b1f9018794d727.jpg",
   "shopName" : "BALNEAIRE范德安旗舰店",
   "time" : 1613564853,
   "totalScore" : "",
   "venderId" : 76265
}
