{
   "PointExSku" : 0,
   "browse" : "WeiXin",
   "discount" : "0.00",
   "env" : 1,
   "errMsg" : "",
   "hasMemPoint" : 0,
   "hasPin" : 0,
   "iRet" : 0,
   "lmVender" : 0,
   "login" : 0,
   "logoUrl" : "//img30.360buyimg.com/popshop/jfs/t1/147612/15/18591/7333/5fd9a9a3E9fc535bc/4ad9a7d1cc8ccfec.gif",
   "memLeveRuleListJson" : [],
   "member" : 0,
   "memberLevel" : 0,
   "memberPoints" : 0,
   "memberTradeCount" : 0,
   "merberTradeAmount" : "0.00",
   "openVip" : 1,
   "pointExCoupon" : 0,
   "shopId" : 10361762,
   "shopLatestSignUrl" : "//img14.360buyimg.com/cms/jfs/t1/167690/7/1068/353170/5ff41910Ee57b8e1c/df7abbaf7d8cd5cd.jpg",
   "shopName" : "九斗才图书专营店",
   "time" : 1613560886,
   "totalScore" : "",
   "venderId" : 10574948
}
