{
   "PointExSku" : 0,
   "browse" : "WeiXin",
   "discount" : "0.00",
   "env" : 1,
   "errMsg" : "",
   "hasMemPoint" : 0,
   "hasPin" : 0,
   "iRet" : 0,
   "lmVender" : 0,
   "login" : 0,
   "logoUrl" : "//img11.360buyimg.com/cms/jfs/t1/129896/12/12963/14065/5f8fa6cbEcc9254ae/62c5ec0127a3f242.jpg",
   "memLeveRuleListJson" : [],
   "member" : 0,
   "memberLevel" : 0,
   "memberPoints" : 0,
   "memberTradeCount" : 0,
   "merberTradeAmount" : "0.00",
   "openVip" : 0,
   "pointExCoupon" : 0,
   "shopId" : 643724,
   "shopLatestSignUrl" : "//img11.360buyimg.com/zx/jfs/t18562/79/2251297232/185392/a9bc9514/5aec30efN3704daaf.jpg",
   "shopName" : "活泉（VAQUA）旗舰店",
   "time" : 1613559288,
   "totalScore" : "",
   "venderId" : 647199
}
