{
   "PointExSku" : 0,
   "browse" : "WeiXin",
   "discount" : "0.00",
   "env" : 1,
   "errMsg" : "",
   "hasMemPoint" : 1,
   "hasPin" : 0,
   "iRet" : 0,
   "lmVender" : 0,
   "login" : 0,
   "logoUrl" : "//img30.360buyimg.com/popshop/jfs/t3874/124/1716053401/13501/88d135d1/5896efeaNf30608b4.jpg",
   "memLeveRuleListJson" : [],
   "member" : 0,
   "memberLevel" : 0,
   "memberPoints" : 0,
   "memberTradeCount" : 0,
   "merberTradeAmount" : "0.00",
   "openVip" : 1,
   "pointExCoupon" : 0,
   "shopId" : 644165,
   "shopLatestSignUrl" : "//img12.360buyimg.com/cms/jfs/t29353/346/1202090218/53206/3e295a59/5cd92b53Nf3079a07.jpg",
   "shopName" : "小新运动专营店",
   "time" : 1613564536,
   "totalScore" : "",
   "venderId" : 647887
}
