{"code":200,"data":{"userActivityStatus":1,"continuePrizeRuleList":[{"level":7,"prizeList":[{"discount":100.00,"type":6,"number":1000,"budgetNum":100000,"userPirzeStatus":1,"class":"com.jd.interact.center.client.api.user.domain.InteractUserPrize","status":2},{"batchKey":"vender_BA#0ce5492d273e416eac9a0fdc095cad7d","prizeStartTime":1612454400000,"expireType":1,"bindType":1,"discount":200.00,"type":1,"number":1000,"budgetNum":1000,"userPirzeStatus":1,"quota":888.00,"prizeEndTime":1614527999000,"validateDay":30,"class":"com.jd.interact.center.client.api.user.domain.InteractUserPrize","status":2}],"signType":1,"days":7,"class":"com.jd.interact.center.client.api.color.domain.sign.ShopSignInteractUserPrizeRule"}],"venderId":10054491,"activityName":"2月份签到","activityStatus":2,"startTime":1612454400000,"endTime":1614527999000,"id":10267975,"class":"com.jd.interact.center.client.api.color.domain.sign.ShopSignActivity","prizeRuleList":[]},"class":"com.jd.interact.center.client.api.common.param.Results","success":true}