{
   "PointExSku" : 0,
   "browse" : "WeiXin",
   "discount" : "0.00",
   "env" : 1,
   "errMsg" : "",
   "hasMemPoint" : 1,
   "hasPin" : 0,
   "iRet" : 0,
   "lmVender" : 0,
   "login" : 0,
   "logoUrl" : "//img30.360buyimg.com/popshop/jfs/t2944/284/2194483935/31947/a5742457/57a04c11N7b5c2523.jpg",
   "memLeveRuleListJson" : [],
   "member" : 0,
   "memberLevel" : 0,
   "memberPoints" : 0,
   "memberTradeCount" : 0,
   "merberTradeAmount" : "0.00",
   "openVip" : 1,
   "pointExCoupon" : 0,
   "shopId" : 1000008744,
   "shopLatestSignUrl" : "//img14.360buyimg.com/cms/jfs/t25876/177/297917014/35199/95efcbdd/5b6aa916Nabaf5ae6.jpg",
   "shopName" : "微兰运动户外京东自营专区",
   "time" : 1613561977,
   "totalScore" : "",
   "venderId" : 1000008744
}
