{
   "PointExSku" : 0,
   "browse" : "WeiXin",
   "discount" : "0.00",
   "env" : 1,
   "errMsg" : "",
   "hasMemPoint" : 1,
   "hasPin" : 0,
   "iRet" : 0,
   "lmVender" : 0,
   "login" : 0,
   "logoUrl" : "//img11.360buyimg.com/cms/jfs/t1/100820/31/14794/12274/5e68b4afEd0b8ad38/4265519fdc1fc14c.gif",
   "memLeveRuleListJson" : [],
   "member" : 0,
   "memberLevel" : 0,
   "memberPoints" : 0,
   "memberTradeCount" : 0,
   "merberTradeAmount" : "0.00",
   "openVip" : 1,
   "pointExCoupon" : 0,
   "shopId" : 590184,
   "shopLatestSignUrl" : "//img13.360buyimg.com/cms/jfs/t1/149391/18/12558/78389/5f9be609Ea7ac2079/4ab6ffeecbc40ea7.jpg",
   "shopName" : "yonex尤尼克斯羽勉专卖店",
   "time" : 1613564380,
   "totalScore" : "",
   "venderId" : 598535
}
