{
   "PointExSku" : 0,
   "browse" : "WeiXin",
   "discount" : "0.00",
   "env" : 1,
   "errMsg" : "",
   "hasMemPoint" : 0,
   "hasPin" : 0,
   "iRet" : 0,
   "lmVender" : 0,
   "login" : 0,
   "logoUrl" : "//img30.360buyimg.com/popshop/jfs/t1/73279/18/9459/20277/5d720f4aE30939b4d/ee50fd9bd4cd4eda.jpg",
   "memLeveRuleListJson" : [],
   "member" : 0,
   "memberLevel" : 0,
   "memberPoints" : 0,
   "memberTradeCount" : 0,
   "merberTradeAmount" : "0.00",
   "openVip" : 1,
   "pointExCoupon" : 0,
   "shopId" : 10093793,
   "shopLatestSignUrl" : "//img11.360buyimg.com/cms/jfs/t1/116744/21/9315/409228/5ed89ef9Efddc0d4e/ce4c5272f3020292.jpg",
   "shopName" : "淘易乐美妆专营店",
   "time" : 1613558257,
   "totalScore" : "",
   "venderId" : 10230274
}
