{
   "PointExSku" : 0,
   "browse" : "WeiXin",
   "discount" : "0.00",
   "env" : 1,
   "errMsg" : "",
   "hasMemPoint" : 1,
   "hasPin" : 0,
   "iRet" : 0,
   "lmVender" : 0,
   "login" : 0,
   "logoUrl" : "//img11.360buyimg.com/jshopm/jfs/t7990/272/1450697639/5363/aece4f6a/599d01b4Ne13a7ded.jpg",
   "memLeveRuleListJson" : [],
   "member" : 0,
   "memberLevel" : 0,
   "memberPoints" : 0,
   "memberTradeCount" : 0,
   "merberTradeAmount" : "0.00",
   "openVip" : 1,
   "pointExCoupon" : 0,
   "shopId" : 1000008533,
   "shopLatestSignUrl" : "//img12.360buyimg.com/cms/jfs/t1/90718/27/15780/315045/5e749499E6796a59f/ce93cc5aad5f2941.jpg",
   "shopName" : "米熙京东自营旗舰店",
   "time" : 1613561976,
   "totalScore" : "",
   "venderId" : 1000008533
}
