{
   "PointExSku" : 0,
   "browse" : "WeiXin",
   "discount" : "0.00",
   "env" : 1,
   "errMsg" : "",
   "hasMemPoint" : 1,
   "hasPin" : 0,
   "iRet" : 0,
   "lmVender" : 0,
   "login" : 0,
   "logoUrl" : "//img11.360buyimg.com/jshopm/jfs/t12049/23/2263614685/7593/b1a9d8e1/5a39f49bN2731273e.jpg",
   "memLeveRuleListJson" : [],
   "member" : 0,
   "memberLevel" : 0,
   "memberPoints" : 0,
   "memberTradeCount" : 0,
   "merberTradeAmount" : "0.00",
   "openVip" : 1,
   "pointExCoupon" : 0,
   "shopId" : 734376,
   "shopLatestSignUrl" : "//img13.360buyimg.com/cms/jfs/t1/71744/26/7092/342823/5d5228cdEf46e746b/d8a2dacad0cec27b.jpg",
   "shopName" : "李宁钒度专卖店",
   "time" : 1613564794,
   "totalScore" : "",
   "venderId" : 739308
}
