{
   "PointExSku" : 0,
   "browse" : "WeiXin",
   "discount" : "0.00",
   "env" : 1,
   "errMsg" : "",
   "hasMemPoint" : 1,
   "hasPin" : 0,
   "iRet" : 0,
   "lmVender" : 0,
   "login" : 0,
   "logoUrl" : "//img13.360buyimg.com/zx/jfs/t18928/23/1175130711/5872/2a1bd25e/5abef8b9N01d70357.jpg",
   "memLeveRuleListJson" : [],
   "member" : 0,
   "memberLevel" : 0,
   "memberPoints" : 0,
   "memberTradeCount" : 0,
   "merberTradeAmount" : "0.00",
   "openVip" : 1,
   "pointExCoupon" : 0,
   "shopId" : 774696,
   "shopLatestSignUrl" : "//img14.360buyimg.com/cms/jfs/t20938/335/475107506/111485/fc8d7471/5b0e43eeN475b696c.jpg",
   "shopName" : "红色小象东汇百川专卖店",
   "time" : 1613559542,
   "totalScore" : "",
   "venderId" : 778657
}
