{
   "PointExSku" : 0,
   "browse" : "WeiXin",
   "discount" : "0.00",
   "env" : 1,
   "errMsg" : "",
   "hasMemPoint" : 0,
   "hasPin" : 0,
   "iRet" : 0,
   "lmVender" : 0,
   "login" : 0,
   "logoUrl" : "//img13.360buyimg.com/cms/jfs/t1/92295/27/17445/5085/5e8586aeEe1ebdd1d/0ba73e775199c93a.png",
   "memLeveRuleListJson" : [],
   "member" : 0,
   "memberLevel" : 0,
   "memberPoints" : 0,
   "memberTradeCount" : 0,
   "merberTradeAmount" : "0.00",
   "openVip" : 0,
   "pointExCoupon" : 0,
   "shopId" : 10188493,
   "shopLatestSignUrl" : "//img13.360buyimg.com/cms/jfs/t1/108702/7/11076/224134/5e8588d1Ecb3e7ab6/aba1bfb600825446.png",
   "shopName" : "棉之润官方旗舰店",
   "time" : 1613558499,
   "totalScore" : "",
   "venderId" : 10334170
}
